configreader/__init__.py
configreader/config.py
spconfigreader/__init__.py
spconfigreader/configreader.py
spconfigreader/reader.py
tests/__init__.py
tests/test.py
spconfigreader-0.3.2.dist-info/LICENSE
spconfigreader-0.3.2.dist-info/METADATA
spconfigreader-0.3.2.dist-info/WHEEL
spconfigreader-0.3.2.dist-info/top_level.txt
spconfigreader-0.3.2.dist-info/RECORD
